buildpy/__init__.py
buildpy/lint_check.py
buildpy/py.typed
buildpy/pyproject.toml
buildpy/security_check.py
buildpy/type_check.py
buildpy/util.py
buildpy/version.py
kiba_build-0.1.10.dist-info/METADATA
kiba_build-0.1.10.dist-info/WHEEL
kiba_build-0.1.10.dist-info/entry_points.txt
kiba_build-0.1.10.dist-info/top_level.txt
kiba_build-0.1.10.dist-info/RECORD
