Metadata-Version: 2.1
Name: kiba-build
Version: 0.1.10
Summary: Kiba Labs' python building and testing utilities
Home-page: https://github.com/kibalabs/build-py
Requires-Python: ~=3.7
Requires-Dist: bump2version~=1.0.1
Requires-Dist: click~=8.1.7
Requires-Dist: asyncclick~=8.1.7.2
Requires-Dist: simple-chalk~=0.1.0
Requires-Dist: pylint~=3.2.6
Requires-Dist: mypy~=1.11.1
Requires-Dist: wheel~=0.44.0
Requires-Dist: bandit~=1.7.9
Requires-Dist: twine~=5.1.1
